{
  "indexes": [
    {
      "collectionGroup": "rooms",
      "queryScope": "COLLECTION",
      "fields": [
        { "fieldPath": "roomCode", "order": "ASCENDING" },
        { "fieldPath": "status", "order": "ASCENDING" }
      ]
    },
    {
      "collectionGroup": "rooms",
      "queryScope": "COLLECTION",
      "fields": [
        { "fieldPath": "isPrivate", "order": "ASCENDING" },
        { "fieldPath": "status", "order": "ASCENDING" },
        { "fieldPath": "createdAt", "order": "DESCENDING" }
      ]
    },
    {
      "collectionGroup": "leaderboard",
      "queryScope": "COLLECTION",
      "fields": [
        { "fieldPath": "wins", "order": "DESCENDING" },
        { "fieldPath": "winRate", "order": "DESCENDING" }
      ]
    }
  ],
  "fieldOverrides": []
}
